<?xml version="1.0" ?><list><sparepart><kode>SP-0001</kode><nama>Oli Mesin 1L</nama><kategori>Oli &amp; Cairan</kategori><stok>19</stok><hargaJual>85000.0</hargaJual><hargaModal>60000.0</hargaModal></sparepart><sparepart><kode>SP-0002</kode><nama>Kampas Rem Depan</nama><kategori>Rem</kategori><stok>3</stok><hargaJual>150000.0</hargaJual><hargaModal>95000.0</hargaModal></sparepart><sparepart><kode>SP-0003</kode><nama>Busi Racing</nama><kategori>Kelistrikan</kategori><stok>50</stok><hargaJual>35000.0</hargaJual><hargaModal>20000.0</hargaModal></sparepart><sparepart><kode>SP-0004</kode><nama>Ban Tubeless 90/80-17</nama><kategori>Ban &amp; Roda</kategori><stok>30</stok><hargaJual>350000.0</hargaJual><hargaModal>260000.0</hargaModal></sparepart><sparepart><kode>SP-0005</kode><nama>Oli Mesin 2L</nama><kategori>Oli &amp; Cairan</kategori><stok>20</stok><hargaJual>850000.0</hargaJual><hargaModal>510000.0</hargaModal></sparepart></list>